secretauth/__init__.py
secretauth/auth.py
secretauth/crypto/__init__.py
secretauth/crypto/hmac256.py
secretauth/exception/__init__.py
secretauth/exception/custom.py
secretauth/secret/__init__.py
secretauth/secret/aws.py
secretauth/secret/local.py
secretauth/secret/provider.py
secretauth-1.0.0.dist-info/licenses/LICENSE
secretauth-1.0.0.dist-info/METADATA
secretauth-1.0.0.dist-info/WHEEL
secretauth-1.0.0.dist-info/top_level.txt
secretauth-1.0.0.dist-info/RECORD
