Metadata-Version: 2.4
Name: secretauth
Version: 1.0.0
Summary: secretauth is a secure, unified solution for generating and validating tokens using secret from multiple cloud platforms.
Author: abhinavkaurav, cloudinduscom
License: MIT
Project-URL: homepage, https://github.com/cloudinduscom/secretauth
Project-URL: source, https://github.com/cloudinduscom/secretauth
Project-URL: issues, https://github.com/cloudinduscom/secretauth/issues
Classifier: Intended Audience :: Developers
Classifier: Intended Audience :: Education
Classifier: License :: OSI Approved :: MIT License
Classifier: Natural Language :: English
Classifier: Operating System :: OS Independent
Classifier: Programming Language :: Python
Classifier: Programming Language :: Python :: 3
Classifier: Programming Language :: Python :: 3.9
Classifier: Programming Language :: Python :: 3.10
Classifier: Programming Language :: Python :: 3.11
Classifier: Programming Language :: Python :: 3.12
Classifier: Programming Language :: Python :: 3.13
Classifier: Programming Language :: Python :: Implementation :: CPython
Classifier: Programming Language :: Python :: Implementation :: PyPy
Classifier: Topic :: Software Development :: Libraries
Classifier: Topic :: Security :: Cryptography
Requires-Python: >=3.9
License-File: LICENSE
Requires-Dist: boto3==1.37.24
Provides-Extra: test
Requires-Dist: pytest>=7.4.0; extra == "test"
Requires-Dist: pytest-cov>=3.0.0; extra == "test"
Requires-Dist: pytest-mock>=3.9.0; extra == "test"
Dynamic: license-file
